anima_core-0.1.1.dist-info/METADATA
anima_core-0.1.1.dist-info/WHEEL
anima_core/__init__.py
anima_core/anima_core.cpython-312-darwin.so
anima_core-0.1.1.dist-info/RECORD
