Metadata-Version: 2.4
Name: anima_core
Version: 0.1.1
